bedrock_chunk_diff-0.4.0.dist-info/licenses/LICENSE
bedrockchunkdiff/__init__.py
bedrockchunkdiff/dynamic_libs/bedrock-chunk-diff_android_arm64.so
bedrockchunkdiff/dynamic_libs/bedrock-chunk-diff_linux_amd64.so
bedrockchunkdiff/dynamic_libs/bedrock-chunk-diff_linux_arm64.so
bedrockchunkdiff/dynamic_libs/bedrock-chunk-diff_macos_amd64.dylib
bedrockchunkdiff/dynamic_libs/bedrock-chunk-diff_macos_arm64.dylib
bedrockchunkdiff/dynamic_libs/bedrock-chunk-diff_windows_amd64.dll
bedrockchunkdiff/dynamic_libs/bedrock-chunk-diff_windows_x86.dll
bedrockchunkdiff/internal/__init__.py
bedrockchunkdiff/internal/load_dynamic_library.py
bedrockchunkdiff/internal/symbol_export_chunk_timeline.py
bedrockchunkdiff/internal/symbol_export_timeline_db.py
bedrockchunkdiff/internal/types.py
bedrockchunkdiff/internal/utils.py
bedrockchunkdiff/timeline/__init__.py
bedrockchunkdiff/timeline/chunk_timeline.py
bedrockchunkdiff/timeline/constant.py
bedrockchunkdiff/timeline/define.py
bedrockchunkdiff/timeline/timeline_database.py
bedrock_chunk_diff-0.4.0.dist-info/METADATA
bedrock_chunk_diff-0.4.0.dist-info/WHEEL
bedrock_chunk_diff-0.4.0.dist-info/top_level.txt
bedrock_chunk_diff-0.4.0.dist-info/RECORD
